ChangeLog
LICENSE
MANIFEST.in
README.md
setup.py
cdmgcplugin.egg-info/PKG-INFO
cdmgcplugin.egg-info/SOURCES.txt
cdmgcplugin.egg-info/dependency_links.txt
cdmgcplugin.egg-info/top_level.txt
cdmplugins/gc/__init__.py
cdmplugins/gc/configdlg.py
cdmplugins/gc/garbagecollector.cdmp