Metadata-Version: 1.1
Name: cdmgcplugin
Version: 1.0.2
Summary: Codimension IDE garbage collector plugin
Home-page: https://github.com/SergeySatskiy/cdm-gc-plugin
Author: Sergey Satskiy
Author-email: sergey.satskiy@gmail.com
License: GPLv3
Platform: any
Classifier: Development Status :: 5 - Production/Stable
Classifier: Intended Audience :: Developers
Classifier: License :: OSI Approved :: GNU General Public License (GPL)
Classifier: Operating System :: POSIX :: Linux
Classifier: Programming Language :: Python :: 3
